{"url": "https://www.sec.gov/Archives/edgar/data/1067983/000095015003000245/index.json", "ts": 1775605575.028311, "content": "{\"directory\":{\"item\":[{\"last-modified\": \"2003-02-24 11:49:06\",\"name\":\"0000950150-03-000245-index-headers.html\",\"type\":\"text.gif\",\"size\":\"\"},{\"last-modified\": \"2003-02-24 11:49:06\",\"name\":\"0000950150-03-000245-index.html\",\"type\":\"text.gif\",\"size\":\"\"},{\"last-modified\": \"2003-02-24 11:49:06\",\"name\":\"0000950150-03-000245.txt\",\"type\":\"text.gif\",\"size\":\"\"},{\"last-modified\": \"2003-02-24 11:49:06\",\"name\":\"a87859ce13fvhrza.txt\",\"type\":\"text.gif\",\"size\":\"5313\"}],\"name\":\"\\/Archives\\/edgar\\/data\\/1067983\\/000095015003000245\",\"parent-dir\":\"\\/Archives\\/edgar\\/data\\/1067983\"}}"}