{"url": "https://www.sec.gov/Archives/edgar/data/1037389/000103738901500005/index.json", "ts": 1775607094.4114041, "content": "{\"directory\":{\"item\":[{\"last-modified\": \"2001-01-30 00:00:00\",\"name\":\"0001037389-01-500005-index-headers.html\",\"type\":\"text.gif\",\"size\":\"\"},{\"last-modified\": \"2001-01-30 00:00:00\",\"name\":\"0001037389-01-500005-index.html\",\"type\":\"text.gif\",\"size\":\"\"},{\"last-modified\": \"2001-01-30 00:00:00\",\"name\":\"0001037389-01-500005.txt\",\"type\":\"text.gif\",\"size\":\"\"},{\"last-modified\": \"2001-01-30 00:00:00\",\"name\":\"r13f99q3.txt\",\"type\":\"text.gif\",\"size\":\"141174\"}],\"name\":\"\\/Archives\\/edgar\\/data\\/1037389\\/000103738901500005\",\"parent-dir\":\"\\/Archives\\/edgar\\/data\\/1037389\"}}"}