{"url": "https://www.sec.gov/Archives/edgar/data/1350694/000114036113006490/index.json", "ts": 1775607110.6635158, "content": "{\"directory\":{\"item\":[{\"last-modified\": \"2013-02-13 17:22:17\",\"name\":\"0001140361-13-006490-index-headers.html\",\"type\":\"text.gif\",\"size\":\"\"},{\"last-modified\": \"2013-02-13 17:22:17\",\"name\":\"0001140361-13-006490-index.html\",\"type\":\"text.gif\",\"size\":\"\"},{\"last-modified\": \"2013-02-13 17:22:17\",\"name\":\"0001140361-13-006490.txt\",\"type\":\"text.gif\",\"size\":\"\"},{\"last-modified\": \"2013-02-13 17:22:17\",\"name\":\"form13fhr.txt\",\"type\":\"text.gif\",\"size\":\"34551\"}],\"name\":\"\\/Archives\\/edgar\\/data\\/1350694\\/000114036113006490\",\"parent-dir\":\"\\/Archives\\/edgar\\/data\\/1350694\"}}"}