{"url": "https://www.sec.gov/Archives/edgar/data/1336528/000117266109000727/index.json", "ts": 1775607078.173266, "content": "{\"directory\":{\"item\":[{\"last-modified\": \"2009-04-22 14:52:47\",\"name\":\"0001172661-09-000727-index-headers.html\",\"type\":\"text.gif\",\"size\":\"\"},{\"last-modified\": \"2009-04-22 14:52:47\",\"name\":\"0001172661-09-000727-index.html\",\"type\":\"text.gif\",\"size\":\"\"},{\"last-modified\": \"2009-04-22 14:52:47\",\"name\":\"0001172661-09-000727.txt\",\"type\":\"text.gif\",\"size\":\"\"},{\"last-modified\": \"2009-04-22 14:52:47\",\"name\":\"pers4q08a1.txt\",\"type\":\"text.gif\",\"size\":\"3081\"}],\"name\":\"\\/Archives\\/edgar\\/data\\/1336528\\/000117266109000727\",\"parent-dir\":\"\\/Archives\\/edgar\\/data\\/1336528\"}}"}