{"url": "https://www.sec.gov/Archives/edgar/data/1037389/000103738908000002/index.json", "ts": 1775607088.952705, "content": "{\"directory\":{\"item\":[{\"last-modified\": \"2008-02-13 15:40:19\",\"name\":\"0001037389-08-000002-index-headers.html\",\"type\":\"text.gif\",\"size\":\"\"},{\"last-modified\": \"2008-02-13 15:40:19\",\"name\":\"0001037389-08-000002-index.html\",\"type\":\"text.gif\",\"size\":\"\"},{\"last-modified\": \"2008-02-13 15:40:19\",\"name\":\"0001037389-08-000002.txt\",\"type\":\"text.gif\",\"size\":\"\"},{\"last-modified\": \"2008-02-13 15:40:19\",\"name\":\"dec0713f.txt\",\"type\":\"text.gif\",\"size\":\"438708\"}],\"name\":\"\\/Archives\\/edgar\\/data\\/1037389\\/000103738908000002\",\"parent-dir\":\"\\/Archives\\/edgar\\/data\\/1037389\"}}"}